.coveragerc
.drone.yml
.gitignore
.gitmodules
.travis.yml
AUTHORS
CHANGES.rst
LICENSE
MANIFEST.in
README.rst
setup.cfg
setup.py
./chemreac/_chemreac.cpp
.ci/copy_tree.sh
.ci/get_sundials.sh
.ci/run_tests.sh
.circleci/config.yml
chemreac/__init__.py
chemreac/_chemreac.cpp
chemreac/_chemreac.pyx
chemreac/_config.py
chemreac/_odesys.py
chemreac/_release.py
chemreac/chemistry.py
chemreac/constants.py
chemreac/core.py
chemreac/integrate.py
chemreac/serialization.py
chemreac/symbolic.py
chemreac/units.py
chemreac.egg-info/PKG-INFO
chemreac.egg-info/SOURCES.txt
chemreac.egg-info/dependency_links.txt
chemreac.egg-info/requires.txt
chemreac.egg-info/top_level.txt
chemreac/include/chemreac.hpp
chemreac/include/chemreac.pxd
chemreac/include/chemreac_util.hpp
chemreac/tests/__init__.py
chemreac/tests/binary_system.json
chemreac/tests/binary_system.png
chemreac/tests/binary_system_blessed.txt
chemreac/tests/four_species.json
chemreac/tests/four_species_blessed.txt
chemreac/tests/four_species_f_jac.png
chemreac/tests/four_species_f_jac_logt.png
chemreac/tests/four_species_f_jac_logy.png
chemreac/tests/only_1_species_diffusion_3bins_logy_formulae.png
chemreac/tests/test_ReactionDiffusion__only_1_reaction__logy.png
chemreac/tests/test_ReactionDiffusion__only_1_reaction__logy_logt.png
chemreac/tests/test_ReactionDiffusion__only_1_species_diffusion_2bins.png
chemreac/tests/test_ReactionDiffusion__only_1_species_diffusion_3bins.png
chemreac/tests/test_ReactionDiffusion__only_1_species_diffusion_3bins_logy.png
chemreac/tests/test_binary_system.py
chemreac/tests/test_chemistry.py
chemreac/tests/test_constants.py
chemreac/tests/test_decay_chain.py
chemreac/tests/test_four_species.py
chemreac/tests/test_integrate.py
chemreac/tests/test_odesys.py
chemreac/tests/test_reactiondiffusion.py
chemreac/tests/test_serialization.py
chemreac/tests/test_symbolic.py
chemreac/util/__init__.py
chemreac/util/_player.py
chemreac/util/analysis.py
chemreac/util/anim.py
chemreac/util/banded.py
chemreac/util/grid.py
chemreac/util/plotting.py
chemreac/util/pyutil.py
chemreac/util/stoich.py
chemreac/util/table.py
chemreac/util/testing.py
