Metadata-Version: 2.1
Name: chemreac
Version: 0.10.1
Summary: Python package for modeling chemical kinetics with diffusion and drift.
Home-page: https://github.com/chemreac/chemreac
Author: Bjoern I. Dahlgren
Author-email: bjodah@gmail.com
License: BSD
Keywords: chemical kinetics,Smoluchowski equation,advection-diffusion-reaction
Platform: UNKNOWN
Classifier: Development Status :: 3 - Alpha
Classifier: License :: OSI Approved :: BSD License
Classifier: Operating System :: OS Independent
Classifier: Programming Language :: Python
Classifier: Topic :: Scientific/Engineering
Classifier: Topic :: Scientific/Engineering :: Mathematics
Requires-Python: >=3.6
Provides-Extra: all
